LICENSE
MANIFEST.in
README.md
requirements.txt
setup.cfg
setup.py
cf_text_embeddings/__init__.py
cf_text_embeddings/downloader.py
cf_text_embeddings/interaction_views.py
cf_text_embeddings/library.py
cf_text_embeddings/urls.py
cf_text_embeddings/version.py
cf_text_embeddings/views.py
cf_text_embeddings/visualization_views.py
cf_text_embeddings.egg-info/PKG-INFO
cf_text_embeddings.egg-info/SOURCES.txt
cf_text_embeddings.egg-info/dependency_links.txt
cf_text_embeddings.egg-info/requires.txt
cf_text_embeddings.egg-info/top_level.txt
cf_text_embeddings/base/__init__.py
cf_text_embeddings/base/common.py
cf_text_embeddings/base/embeddings_model.py
cf_text_embeddings/base/io.py
cf_text_embeddings/base/table.py
cf_text_embeddings/base/tokenizers.py
cf_text_embeddings/corpus/basic.tsv
cf_text_embeddings/models/test/word2vec_test_model.bin
cf_text_embeddings/package_data/categories/2da132ad-2c50-4f4f-b79a-cb0579c7b70f.json
cf_text_embeddings/package_data/categories/2f08e379-6137-45d1-b880-7c1be11e67c5.json
cf_text_embeddings/package_data/categories/64066a04-05fe-4d9a-b380-f2627846a232.json
cf_text_embeddings/package_data/categories/9efeb445-5e78-4a98-af9b-3b1f8120728b.json
cf_text_embeddings/package_data/categories/c15657c5-4927-4ea6-b48f-e6a26c011a7c.json
cf_text_embeddings/package_data/categories/cb7fc8c2-0f8a-4bd6-a625-ed1a7ebe03a7.json
cf_text_embeddings/package_data/widgets/09bc6245-a8fe-4a99-9f11-823e7fcfe27e.json
cf_text_embeddings/package_data/widgets/0ab13a3d-20bc-421a-b388-933b8e9d5de1.json
cf_text_embeddings/package_data/widgets/1b7bd212-9465-46ce-be5d-ec5ae4342f8a.json
cf_text_embeddings/package_data/widgets/43827ef5-f7ad-4d92-9c93-17b54d127540.json
cf_text_embeddings/package_data/widgets/4aa9c792-0aff-4ba3-8834-7b87269b95d8.json
cf_text_embeddings/package_data/widgets/532b6da3-718e-4707-b43b-ada1234b0663.json
cf_text_embeddings/package_data/widgets/5d5ec104-e5e2-442d-a868-1408631ba834.json
cf_text_embeddings/package_data/widgets/5e483f0a-1110-4978-81e5-8a06ee7719ee.json
cf_text_embeddings/package_data/widgets/645fe5bc-2bd5-421c-9c4a-7d9859c34074.json
cf_text_embeddings/package_data/widgets/6e75e115-aeda-4868-a473-9eb5cce36090.json
