Metadata-Version: 1.0
Name: cf-text-embeddings
Version: 0.1.28
Summary: Text Embeddings for ClowdFlows
Home-page: https://github.com/xflows/cf_text_embeddings
Author: Roman Orac
Author-email: orac.roman@gmail.com
License: MIT License
Platform: UNKNOWN
